dogsvscats/__init__.py
dogsvscats/predict.py
venv/bin/rst2html.py
venv/bin/rst2html4.py
venv/bin/rst2html5.py
venv/bin/rst2latex.py
venv/bin/rst2man.py
venv/bin/rst2odt.py
venv/bin/rst2odt_prepstyles.py
venv/bin/rst2pseudoxml.py
venv/bin/rst2s5.py
venv/bin/rst2xetex.py
venv/bin/rst2xml.py
venv/bin/rstpep2html.py
venv/bin/wsdump.py
dogsvscats-0.2.2.dist-info/METADATA
dogsvscats-0.2.2.dist-info/WHEEL
dogsvscats-0.2.2.dist-info/top_level.txt
dogsvscats-0.2.2.dist-info/RECORD
